README.md
setup.py
fusionfusion/__init__.py
fusionfusion/annotationFunction.py
fusionfusion/arg_parser.py
fusionfusion/cigar_utils.py
fusionfusion/config.py
fusionfusion/filterJunctionInfo.py
fusionfusion/parseJunctionInfo.py
fusionfusion/region_utils.py
fusionfusion/regions.py
fusionfusion/run.py
fusionfusion/seq_utils.py
fusionfusion/utils.py
fusionfusion/version.py
fusionfusion.egg-info/PKG-INFO
fusionfusion.egg-info/SOURCES.txt
fusionfusion.egg-info/dependency_links.txt
fusionfusion.egg-info/entry_points.txt
fusionfusion.egg-info/top_level.txt